mat3ra/__init__.py
mat3ra/fixtures/__init__.py
mat3ra/fixtures/manifest.yml
mat3ra/fixtures/data/applications/espresso/5.4.0/manifest.yml
mat3ra/fixtures/data/applications/espresso/5.4.0/case-001/pw-scf.in
mat3ra/fixtures/data/applications/espresso/5.4.0/case-001/pw-scf.out
mat3ra/fixtures/data/applications/espresso/5.4.0/case-001/run.sh
mat3ra/fixtures/data/applications/espresso/5.4.0/case-001/outdir/__prefix__.save/charge-density.dat
mat3ra/fixtures/data/applications/espresso/5.4.0/case-001/outdir/__prefix__.save/data-file.xml
mat3ra/fixtures/data/applications/espresso/5.4.0/case-001/outdir/__prefix__.save/gvectors.dat
mat3ra/fixtures/data/applications/espresso/5.4.0/case-001/outdir/__prefix__.save/si_pbe_gbrv_1.0.upf
mat3ra/fixtures/data/applications/espresso/5.4.0/case-001/outdir/__prefix__.save/K00001/eigenval.xml
mat3ra/fixtures/data/applications/espresso/5.4.0/case-001/outdir/__prefix__.save/K00001/evc.dat
mat3ra/fixtures/data/applications/espresso/5.4.0/case-001/outdir/__prefix__.save/K00001/gkvectors.dat
mat3ra/fixtures/data/applications/espresso/5.4.0/case-001/outdir/__prefix__.save/K00002/eigenval.xml
mat3ra/fixtures/data/applications/espresso/5.4.0/case-001/outdir/__prefix__.save/K00002/evc.dat
mat3ra/fixtures/data/applications/espresso/5.4.0/case-001/outdir/__prefix__.save/K00002/gkvectors.dat
mat3ra/fixtures/data/applications/espresso/5.4.0/case-001/outdir/__prefix__.save/K00003/eigenval.xml
mat3ra/fixtures/data/applications/espresso/5.4.0/case-001/outdir/__prefix__.save/K00003/evc.dat
mat3ra/fixtures/data/applications/espresso/5.4.0/case-001/outdir/__prefix__.save/K00003/gkvectors.dat
mat3ra/fixtures/data/applications/espresso/5.4.0/case-001/outdir/__prefix__.save/K00004/eigenval.xml
mat3ra/fixtures/data/applications/espresso/5.4.0/case-001/outdir/__prefix__.save/K00004/evc.dat
mat3ra/fixtures/data/applications/espresso/5.4.0/case-001/outdir/__prefix__.save/K00004/gkvectors.dat
mat3ra_fixtures-2024.4.6.post0.dist-info/LICENSE.md
mat3ra_fixtures-2024.4.6.post0.dist-info/METADATA
mat3ra_fixtures-2024.4.6.post0.dist-info/WHEEL
mat3ra_fixtures-2024.4.6.post0.dist-info/top_level.txt
mat3ra_fixtures-2024.4.6.post0.dist-info/RECORD
